LICENSE
README.md
pyproject.toml
setup.py
wasm_runtime/__init__.py
wasm_runtime/_get_runtime.py
wasm_runtime/runtime.py
wasm_runtime.egg-info/.gitignore
wasm_runtime.egg-info/PKG-INFO
wasm_runtime.egg-info/SOURCES.txt
wasm_runtime.egg-info/dependency_links.txt
wasm_runtime.egg-info/requires.txt
wasm_runtime.egg-info/top_level.txt