Metadata-Version: 2.1
Name: wasm-runtime
Version: 0.2
Summary: WebAssembly-powered, sandboxed implementation of Python runtime for safely exec()-cuting dynamic Python code.
Author-email: AWeirdDev <aweirdscratcher@gmail.com>
License: MIT License
Project-URL: Source, https://github.com/AWeirdScratcher/wasm_runtime
Project-URL: Bug Tracker, https://github.com/AWeirdScratcher/wasm_runtime/issues
Keywords: wasm,runtime,python,sandbox,restricted,limited
Classifier: Programming Language :: Python :: 3
Classifier: License :: OSI Approved :: MIT License
Classifier: Operating System :: OS Independent
Requires-Python: >=3
License-File: LICENSE
Requires-Dist: requests
